commit_buddy/__init__.py
commit_buddy/main.py
commit_buddy-0.1.0.dist-info/METADATA
commit_buddy-0.1.0.dist-info/WHEEL
commit_buddy-0.1.0.dist-info/entry_points.txt
commit_buddy-0.1.0.dist-info/top_level.txt
commit_buddy-0.1.0.dist-info/RECORD
