Metadata-Version: 2.2
Name: commit-buddy
Version: 0.1.0
Summary: AI-Powered Git Commit Assistant
Author: @atom2ueki
License: MIT
Project-URL: Homepage, https://github.com/atom2ueki/commitbuddy
Project-URL: Repository, https://github.com/atom2ueki/commitbuddy.git
Keywords: git,commit,ai,ollama
Classifier: Programming Language :: Python :: 3
Classifier: Environment :: Console
Classifier: Intended Audience :: Developers
Classifier: Topic :: Software Development :: Version Control :: Git
Requires-Python: >=3.6
Requires-Dist: requests>=2.31.0
Requires-Dist: PyYAML>=6.0.1
